<contact_sheet>
  <unique_identifier></unique_identifier>
  <identifiers>
    <identifier></identifier>
    <catalog_number></catalog_number>
  </identifiers>
  <rights_statement></rights_statement>
  <people>
    <person_id></person_id>
    <person_id></person_id>
  </people>
  <has_many>
    <card_id></card_id>
    <card_id></card_id>
  </has_many>
  <belongs_to>
    <card_id></card_id>
    <card_id></card_id>
  </belongs_to>
  <photographic_image_metadata></photographic_image_metadata>
  <contact_sheet_metadata>
    <negatives>
      <negative_id></negative_id>
      <negative_id></negative_id>
    </negatives>
    ... contact-sheet-specific metadata
  </contact_sheet_metadata>
</contact_sheet>